pg_probackup2/__init__.py
pg_probackup2/app.py
pg_probackup2/gdb.py
pg_probackup2/init_helpers.py
pg_probackup2/storage/__init__.py
pg_probackup2/storage/fs_backup.py
testgres_pg_probackup2-0.2.2.dist-info/METADATA
testgres_pg_probackup2-0.2.2.dist-info/WHEEL
testgres_pg_probackup2-0.2.2.dist-info/top_level.txt
testgres_pg_probackup2-0.2.2.dist-info/RECORD
