Metadata-Version: 2.4
Name: testgres_pg_probackup2
Version: 0.2.2
Summary: Plugin for testgres that manages pg_probackup2
Home-page: https://github.com/postgrespro/testgres
Author: Postgres Professional
Author-email: testgres@postgrespro.ru
License: PostgreSQL
Keywords: pg_probackup,testing,testgres
Requires-Dist: testgres>=1.9.2
Dynamic: author
Dynamic: author-email
Dynamic: description-content-type
Dynamic: home-page
Dynamic: keywords
Dynamic: license
Dynamic: requires-dist
Dynamic: summary
